LICENSE
admin_tabs/__init__.py
admin_tabs/apps.py
admin_tabs/checks.py
admin_tabs/decorators.py
admin_tabs/exceptions.py
admin_tabs/filters.py
admin_tabs/options.py
admin_tabs/templates/admin_tabs/admin/change_list.html
admin_tabs/templates/admin_tabs/admin/tab_filter.html
admin_tabs/views.py
django_admin_tabs-0.0.1.dist-info/LICENSE
django_admin_tabs-0.0.1.dist-info/METADATA
django_admin_tabs-0.0.1.dist-info/WHEEL
django_admin_tabs-0.0.1.dist-info/RECORD
