Metadata-Version: 2.1
Name: django-admin-tabs
Version: 0.0.1
Summary: It generates tabs for Django admin's changelist
Home-page: https://github.com/valbertovc/django-admin-tabs
Keywords: django,admin,filter,tabs
Author: Valberto Carneiro
Author-email: valbertovc@gmail.com
Requires-Python: >=3.8,<4
Classifier: Development Status :: 4 - Beta
Classifier: Framework :: Django :: 2
Classifier: Framework :: Django :: 2.2
Classifier: Framework :: Django :: 3
Classifier: Framework :: Django :: 3.2
Classifier: Framework :: Django :: 4
Classifier: Framework :: Django :: 4.1
Classifier: Framework :: Django :: 5.0
Classifier: Intended Audience :: Developers
Classifier: License :: OSI Approved :: MIT License
Classifier: Operating System :: OS Independent
Classifier: Programming Language :: Python
Classifier: Programming Language :: Python :: 3
Classifier: Programming Language :: Python :: 3.8
Classifier: Programming Language :: Python :: 3.9
Classifier: Programming Language :: Python :: 3.10
Classifier: Programming Language :: Python :: 3.11
Classifier: Programming Language :: Python :: 3.12
Classifier: Topic :: Software Development :: Libraries :: Application Frameworks
Requires-Dist: Django (>=4.0.0)
Project-URL: Bug Tracker, https://github.com/valbertovc/django-admin-tabs/issues
Project-URL: Changelog, https://github.com/valbertovc/django-admin-tabs/releases
Project-URL: Homepage, https://valbertovc.github.io/django-admin-tabs/
Project-URL: Repository, https://github.com/valbertovc/django-admin-tabs
